[
  {
    "slug": "yokohama",
    "name": "横浜市",
    "cities": ["横浜市"],
    "summary": "医療依存度が高い方の受け入れ先が限られるため、早めの相談が重要です。"
  },
  {
    "slug": "kawasaki",
    "name": "川崎市",
    "cities": ["川崎市"],
    "summary": "医療対応施設の空室が変動しやすいため、最新状況の確認が必須です。"
  },
  {
    "slug": "fujisawa",
    "name": "藤沢市",
    "cities": ["藤沢市"],
    "summary": "在宅医療からの移行相談が多く、看護体制の確認がポイントです。"
  },
  {
    "slug": "chigasaki",
    "name": "茅ヶ崎市",
    "cities": ["茅ヶ崎市"],
    "summary": "看取りまで見据えた医療対応を希望されるご家庭が増えています。"
  },
  {
    "slug": "sagamihara",
    "name": "相模原市",
    "cities": ["相模原市"],
    "summary": "長期の医療連携が必要なケースが多く、施設の連携体制が重要です。"
  },
  {
    "slug": "yokosuka",
    "name": "横須賀市",
    "cities": ["横須賀市"],
    "summary": "医療処置に強い施設が限られるため、早めの比較が必要です。"
  },
  {
    "slug": "atsugi",
    "name": "厚木市",
    "cities": ["厚木市"],
    "summary": "病院連携の有無で受け入れ可否が変わるため相談時に確認します。"
  },
  {
    "slug": "hiratsuka",
    "name": "平塚市",
    "cities": ["平塚市"],
    "summary": "短期入居から中長期の相談まで幅広く対応できる施設探しが鍵です。"
  },
  {
    "slug": "odawara",
    "name": "小田原市",
    "cities": ["小田原市"],
    "summary": "看取り対応の相談が多く、医療体制と費用の確認が重要です。"
  }
]
